<?xml version='1.0' encoding='utf-8'?>
<asset name="Bogota, Bogota">
  <pos>
    <x>7017.361490</x>
    <y>38201.115369</y>
  </pos>
  <GFX>
    <space>mapped/Bogota, Bogota.png</space>
    <exterior>methane.png</exterior>
  </GFX>
  <presence>
    <faction>Za'lek</faction>
    <value>1.000000</value>
    <range>1</range>
  </presence>
  <general>
    <class>M</class>
    <population>7772000</population>
    <hide>0.000000</hide>
    <services>
      <land/>
      <refuel/>
      <bar/>
      <missions/>
      <commodity/>
      <outfits/>
    </services>
    <commodities>
      <commodity>Food</commodity>
      <commodity>Ore</commodity>
      <commodity>Industrial Goods</commodity>
      <commodity>Medicine</commodity>
      <commodity>Luxury Goods</commodity>
    </commodities>
    <description>Bogota, Bogota is in the Bogota system.It is part of Colombia in the Federal District of Bogota.</description>
    <bar>Humans often drink at bars...</bar>
  </general>
  <tech>
    <item>Basic Outfits 2</item>
  </tech>
</asset>
