<?xml version='1.0' encoding='utf-8'?>
<asset name="Calgary, Alberta">
  <pos>
    <x>-35827.712561</x>
    <y>10093.660943</y>
  </pos>
  <GFX>
    <space>mapped/Calgary, Alberta.png</space>
    <exterior>oceanic.png</exterior>
  </GFX>
  <presence>
    <faction>Empire</faction>
    <value>1.000000</value>
    <range>1</range>
  </presence>
  <general>
    <class>M</class>
    <population>1110000</population>
    <hide>0.000000</hide>
    <services>
      <land/>
      <refuel/>
      <bar/>
      <missions/>
      <commodity/>
      <outfits/>
    </services>
    <commodities>
      <commodity>Food</commodity>
      <commodity>Ore</commodity>
      <commodity>Industrial Goods</commodity>
      <commodity>Medicine</commodity>
      <commodity>Luxury Goods</commodity>
    </commodities>
    <description>Calgary, Alberta is in the Calgary system.It is part of Canada in the Province of Alberta.</description>
    <bar>Humans often drink at bars...</bar>
  </general>
  <tech>
    <item>Basic Outfits 2</item>
  </tech>
</asset>
