<?xml version='1.0' encoding='utf-8'?>
<asset name="Doha, Ad Dawhah">
  <pos>
    <x>-27267.056846</x>
    <y>3706.608071</y>
  </pos>
  <GFX>
    <space>mapped/Doha, Ad Dawhah.png</space>
    <exterior>aquatic3.png</exterior>
  </GFX>
  <presence>
    <faction>Goddard</faction>
    <value>1.000000</value>
    <range>1</range>
  </presence>
  <general>
    <class>M</class>
    <population>1450000</population>
    <hide>0.000000</hide>
    <services>
      <land/>
      <refuel/>
      <bar/>
      <missions/>
      <commodity/>
      <outfits/>
    </services>
    <commodities>
      <commodity>Food</commodity>
      <commodity>Ore</commodity>
      <commodity>Industrial Goods</commodity>
      <commodity>Medicine</commodity>
      <commodity>Luxury Goods</commodity>
    </commodities>
    <description>Doha, Ad Dawhah is in the Ad Damman system.It is part of Qatar in the Municipality of Ad Dawhah.</description>
    <bar>Humans often drink at bars...</bar>
  </general>
  <tech>
    <item>Basic Outfits 2</item>
  </tech>
</asset>
