<?xml version='1.0' encoding='utf-8'?>
<asset name="Faleolo, Aiga-i-le-Tai">
  <pos>
    <x>-14176.577746</x>
    <y>10754.149341</y>
  </pos>
  <GFX>
    <space>mapped/Faleolo, Aiga-i-le-Tai.png</space>
    <exterior>aquatic2.png</exterior>
  </GFX>
  <presence>
    <faction>Sirius</faction>
    <value>1.000000</value>
    <range>1</range>
  </presence>
  <general>
    <class>M</class>
    <population>0</population>
    <hide>0.000000</hide>
    <services>
      <land/>
      <refuel/>
      <bar/>
      <outfits/>
    </services>
    <commodities/>
    <description>Faleolo, Aiga-i-le-Tai is in the Apia system. in the area of Aiga-i-le-Tai.</description>
    <bar>This is the officer's lounge</bar>
  </general>
  <tech>
    <item>All Outfits</item>
  </tech>
</asset>
