<?xml version='1.0' encoding='utf-8'?>
<asset name="Jakarta, Jakarta Raya">
  <pos>
    <x>-603.105900</x>
    <y>-7965.614774</y>
  </pos>
  <GFX>
    <space>mapped/Jakarta, Jakarta Raya.png</space>
    <exterior>mining5.png</exterior>
  </GFX>
  <presence>
    <faction>Goddard</faction>
    <value>1.000000</value>
    <range>1</range>
  </presence>
  <general>
    <class>M</class>
    <population>9125000</population>
    <hide>0.000000</hide>
    <services>
      <land/>
      <refuel/>
      <bar/>
      <missions/>
      <commodity/>
      <outfits/>
    </services>
    <commodities>
      <commodity>Food</commodity>
      <commodity>Ore</commodity>
      <commodity>Industrial Goods</commodity>
      <commodity>Medicine</commodity>
      <commodity>Luxury Goods</commodity>
    </commodities>
    <description>Jakarta, Jakarta Raya is in the Jakarta system.It is part of Indonesia in the Special district of Jakarta Raya.</description>
    <bar>Humans often drink at bars...</bar>
  </general>
  <tech>
    <item>Basic Outfits 2</item>
  </tech>
</asset>
