<?xml version='1.0' encoding='utf-8'?>
<asset name="Kugluktuk, Nunavut">
  <pos>
    <x>25107.036616</x>
    <y>23803.462589</y>
  </pos>
  <GFX>
    <space>mapped/Kugluktuk, Nunavut.png</space>
    <exterior>snowy_cliffs.png</exterior>
  </GFX>
  <presence>
    <faction>Empire</faction>
    <value>1.000000</value>
    <range>1</range>
  </presence>
  <general>
    <class>M</class>
    <population>1302</population>
    <hide>0.000000</hide>
    <services>
      <land/>
      <refuel/>
      <bar/>
      <missions/>
      <commodity/>
      <outfits/>
    </services>
    <commodities>
      <commodity>Food</commodity>
      <commodity>Ore</commodity>
      <commodity>Industrial Goods</commodity>
      <commodity>Medicine</commodity>
      <commodity>Luxury Goods</commodity>
    </commodities>
    <description>Kugluktuk, Nunavut is in the Yellowknife system.It is part of Canada in the Territory of Nunavut.</description>
    <bar>Humans often drink at bars...</bar>
  </general>
  <tech>
    <item>Basic Outfits 1</item>
  </tech>
</asset>
