<?xml version='1.0' encoding='utf-8'?>
<asset name="Lahore, Punjab">
  <pos>
    <x>16689.751364</x>
    <y>-26090.500841</y>
  </pos>
  <GFX>
    <space>mapped/Lahore, Punjab.png</space>
    <exterior>aquatic2.png</exterior>
  </GFX>
  <presence>
    <faction>Goddard</faction>
    <value>1.000000</value>
    <range>1</range>
  </presence>
  <general>
    <class>M</class>
    <population>6577000</population>
    <hide>0.000000</hide>
    <services>
      <land/>
      <refuel/>
      <bar/>
      <missions/>
      <commodity/>
      <outfits/>
    </services>
    <commodities>
      <commodity>Food</commodity>
      <commodity>Ore</commodity>
      <commodity>Industrial Goods</commodity>
      <commodity>Medicine</commodity>
      <commodity>Luxury Goods</commodity>
    </commodities>
    <description>Lahore, Punjab is in the Lahore system.It is part of Pakistan in the Province of Punjab.</description>
    <bar>Humans often drink at bars...</bar>
  </general>
  <tech>
    <item>Basic Outfits 2</item>
  </tech>
</asset>
