<?xml version='1.0' encoding='utf-8'?>
<asset name="Maiduguri DNMA Stn">
  <pos>
    <x>11560.472130</x>
    <y>16241.930551</y>
  </pos>
  <GFX>
    <space>station-fleetbase3.png</space>
    <exterior>station03.png</exterior>
  </GFX>
  <presence>
    <faction>Dvaered</faction>
    <value>100.000000</value>
    <range>8</range>
  </presence>
  <general>
    <class>M</class>
    <population>0</population>
    <hide>0.000000</hide>
    <services>
      <land/>
      <refuel/>
      <bar/>
      <outfits/>
    </services>
    <commodities/>
    <description>Maiduguri DNMA Stn is in the Kano system. in the State of Borno.</description>
    <bar>This is the officer's lounge</bar>
  </general>
  <tech>
    <item>All Outfits</item>
  </tech>
</asset>
