<?xml version='1.0' encoding='utf-8'?>
<asset name="Mindelo, Sao Vicente">
  <pos>
    <x>-15992.553580</x>
    <y>-23515.748700</y>
  </pos>
  <GFX>
    <space>mapped/Mindelo, Sao Vicente.png</space>
    <exterior>oceanic.png</exterior>
  </GFX>
  <presence>
    <faction>Dvaered</faction>
    <value>1.000000</value>
    <range>1</range>
  </presence>
  <general>
    <class>M</class>
    <population>70611</population>
    <hide>0.000000</hide>
    <services>
      <land/>
      <refuel/>
      <bar/>
      <missions/>
      <commodity/>
      <outfits/>
    </services>
    <commodities>
      <commodity>Food</commodity>
      <commodity>Ore</commodity>
      <commodity>Industrial Goods</commodity>
      <commodity>Medicine</commodity>
      <commodity>Luxury Goods</commodity>
    </commodities>
    <description>Mindelo, Sao Vicente is in the Praia system.It is part of Cape Verde in the area of Sao Vicente.</description>
    <bar>Humans often drink at bars...</bar>
  </general>
  <tech>
    <item>Basic Outfits 1</item>
  </tech>
</asset>
