<?xml version='1.0' encoding='utf-8'?>
<asset name="Nikolski, Alaska">
  <pos>
    <x>10860.499006</x>
    <y>-15078.367514</y>
  </pos>
  <GFX>
    <space>mapped/Nikolski, Alaska.png</space>
    <exterior>mining3.png</exterior>
  </GFX>
  <presence>
    <faction>Pirate</faction>
    <value>1.000000</value>
    <range>1</range>
  </presence>
  <general>
    <class>M</class>
    <population>18</population>
    <hide>0.000000</hide>
    <services>
      <land/>
      <refuel/>
      <bar/>
      <missions/>
      <commodity/>
      <outfits/>
    </services>
    <commodities>
      <commodity>Food</commodity>
      <commodity>Ore</commodity>
      <commodity>Industrial Goods</commodity>
      <commodity>Medicine</commodity>
      <commodity>Luxury Goods</commodity>
    </commodities>
    <description>Nikolski, Alaska is in the Unalaska system.It is part of United States of America in the State of Alaska.</description>
    <bar>Humans often drink at bars...</bar>
  </general>
  <tech>
    <item>Basic Outfits 1</item>
  </tech>
</asset>
