<?xml version='1.0' encoding='utf-8'?>
<asset name="Tunis, Tunis">
  <pos>
    <x>-11683.215206</x>
    <y>-24163.614910</y>
  </pos>
  <GFX>
    <space>mapped/Tunis, Tunis.png</space>
    <exterior>mining3.png</exterior>
  </GFX>
  <presence>
    <faction>Proteron</faction>
    <value>1.000000</value>
    <range>1</range>
  </presence>
  <general>
    <class>M</class>
    <population>2412500</population>
    <hide>0.000000</hide>
    <services>
      <land/>
      <refuel/>
      <bar/>
      <missions/>
      <commodity/>
      <outfits/>
    </services>
    <commodities>
      <commodity>Food</commodity>
      <commodity>Ore</commodity>
      <commodity>Industrial Goods</commodity>
      <commodity>Medicine</commodity>
      <commodity>Luxury Goods</commodity>
    </commodities>
    <description>Tunis, Tunis is in the Rome system.It is part of Tunisia in the Governorate of Tunis.</description>
    <bar>Humans often drink at bars...</bar>
  </general>
  <tech>
    <item>Basic Outfits 2</item>
  </tech>
</asset>
