<?xml version='1.0' encoding='utf-8'?>
<asset name="Vallenar, Atacama">
  <pos>
    <x>33619.625950</x>
    <y>12854.147132</y>
  </pos>
  <GFX>
    <space>mapped/Vallenar, Atacama.png</space>
    <exterior>aquatic.png</exterior>
  </GFX>
  <presence>
    <faction>Za'lek</faction>
    <value>1.000000</value>
    <range>1</range>
  </presence>
  <general>
    <class>M</class>
    <population>44895</population>
    <hide>0.000000</hide>
    <services>
      <land/>
      <refuel/>
      <bar/>
      <missions/>
      <commodity/>
      <outfits/>
    </services>
    <commodities>
      <commodity>Food</commodity>
      <commodity>Ore</commodity>
      <commodity>Industrial Goods</commodity>
      <commodity>Medicine</commodity>
      <commodity>Luxury Goods</commodity>
    </commodities>
    <description>Vallenar, Atacama is in the Valparaiso system.It is part of Chile in the Region of Atacama.</description>
    <bar>Humans often drink at bars...</bar>
  </general>
  <tech>
    <item>Basic Outfits 1</item>
  </tech>
</asset>
